dekogen_cmd.py
dekogen/base_codegen.py
dekogen/file_writer.py
dekogen/spec_codegen.py
dekogen/spec_reader.py
dekogen-0.1.dist-info/LICENSE
dekogen-0.1.dist-info/METADATA
dekogen-0.1.dist-info/WHEEL
dekogen-0.1.dist-info/entry_points.txt
dekogen-0.1.dist-info/top_level.txt
dekogen-0.1.dist-info/RECORD
