Metadata-Version: 2.1
Name: dekogen
Version: 0.1
Summary: Simple util for generate helper code based on OpenAPI specs
Home-page: https://github.com/denys-ops/dekogen
Author: Denys V. Kondratiuk
License: UNKNOWN
Platform: UNKNOWN
Classifier: Programming Language :: Python :: 3
Classifier: License :: OSI Approved :: MIT License
Requires-Python: >=3.5
Requires-Dist: inflection (==0.3.1)
Requires-Dist: PyYAML (==5.1.2)
Requires-Dist: Click (==7.0)
